CONTRIBUTORS.rst
LICENSE.txt
MANIFEST.in
README.rst
ikpdb.py
iksettrace.c
setup.py
ikpdb.egg-info/PKG-INFO
ikpdb.egg-info/SOURCES.txt
ikpdb.egg-info/dependency_links.txt
ikpdb.egg-info/top_level.txt