Metadata-Version: 1.1
Name: ikpdb
Version: 1.2.1
Summary: A hackable CPython remote debugger designed for the Web and online IDE integration.
Home-page: https://github.com/audaxis/ikpdb
Author: Cyril MORISSE, Audaxis
Author-email: cmorisse@boxes3.net
License: MIT
Keywords: debugger debug remote tcp
Platform: UNKNOWN
Classifier: Development Status :: 4 - Beta
Classifier: Environment :: Web Environment
Classifier: Intended Audience :: Developers
Classifier: Topic :: Software Development :: Debuggers
Classifier: License :: OSI Approved :: MIT License
Classifier: Programming Language :: Python
Classifier: Natural Language :: English
